Volcano_Status/__init__.py
IndonesiaVolcanoStatusByFaqih-0.0.1.dist-info/LICENSE
IndonesiaVolcanoStatusByFaqih-0.0.1.dist-info/METADATA
IndonesiaVolcanoStatusByFaqih-0.0.1.dist-info/WHEEL
IndonesiaVolcanoStatusByFaqih-0.0.1.dist-info/top_level.txt
IndonesiaVolcanoStatusByFaqih-0.0.1.dist-info/RECORD
